MANIFEST.in
README.rst
setup.py
Alchemytools.egg-info/PKG-INFO
Alchemytools.egg-info/SOURCES.txt
Alchemytools.egg-info/dependency_links.txt
Alchemytools.egg-info/requires.txt
Alchemytools.egg-info/top_level.txt
alchemytools/__init__.py
alchemytools/callback.py
alchemytools/context.py