Metadata-Version: 1.1
Name: Alchemytools
Version: 0.2
Summary: Alchemytools is a set of helpers to be used in any SQLAlchemy project
Home-page: https://github.com/daltonmatos/alchemytools
Author: Dalton Barreto
Author-email: daltonmatos@gmail.com
License: UNKNOWN
Platform: UNKNOWN
Classifier: Intended Audience :: Developers
Classifier: License :: OSI Approved :: BSD License
Classifier: Programming Language :: Python
Classifier: Programming Language :: Python :: 2.6
Classifier: Topic :: Software Development
Classifier: Topic :: Software Development :: Libraries
Classifier: Topic :: Software Development :: Libraries :: Python Modules
